[{"customer_id":1,"full_name":"Halsy Egalton","age":20,"email":"hegalton0@bizjournals.com","address":"0 Messerschmidt Pass"},
{"customer_id":2,"full_name":"Margaretta Chree","age":85,"email":"mchree1@abc.net.au","address":"046 Dottie Trail"},
{"customer_id":3,"full_name":"Derry Fleeming","age":38,"email":"dfleeming2@cdc.gov","address":"6 Springs Terrace"},
{"customer_id":27,"full_name":"Hillery Szymon","age":52,"email":"hszymonq@spotify.com","address":"8097 Coleman Park"},
{"customer_id":28,"full_name":"Gayleen Khomich","age":87,"email":"gkhomichr@behance.net","address":"5209 Linden Place"},
{"customer_id":29,"full_name":"Sargent Henrichs","age":93,"email":"shenrichss@gnu.org","address":"4032 Express Center"},
{"customer_id":30,"full_name":"Antonella Ibbeson","age":88,"email":"aibbesont@microsoft.com","address":"2 Transport Court"},
{"customer_id":31,"full_name":"Eda Bygate","age":70,"email":"ebygateu@admin.ch","address":"63 Anzinger Alley"},
{"customer_id":32,"full_name":"Glenn Mendez","age":22,"email":"gmendezv@baidu.com","address":"5 Manufacturers Avenue"},
{"customer_id":33,"full_name":"Haley Bibey","age":51,"email":"hbibeyw@dmoz.org","address":"4 Summerview Crossing"},
{"customer_id":34,"full_name":"Mort Dibbs","age":54,"email":"mdibbsx@sciencedirect.com","address":"5057 Namekagon Crossing"},
{"customer_id":35,"full_name":"Kris Josebury","age":54,"email":"kjoseburyy@godaddy.com","address":"3756 Clemons Street"},
{"customer_id":36,"full_name":"Adelle Comusso","age":37,"email":"acomussoz@bloglines.com","address":"29 Anhalt Circle"},
{"customer_id":37,"full_name":"Shirlee Jery","age":26,"email":"sjery10@addthis.com","address":"39510 Fieldstone Park"},
{"customer_id":38,"full_name":"Eyde Brearty","age":30,"email":"ebrearty11@stumbleupon.com","address":"14053 Helena Crossing"},
{"customer_id":39,"full_name":"Silvano de Almeida","age":48,"email":"sde12@stumbleupon.com","address":"523 Gerald Hill"},
{"customer_id":40,"full_name":"Petronille Schneider","age":78,"email":"pschneider13@nbcnews.com","address":"3170 Dayton Park"},
{"customer_id":41,"full_name":"Toddy Van Castele","age":28,"email":"tvan14@slate.com","address":"38305 Sloan Drive"},
{"customer_id":42,"full_name":"Ronald Umbert","age":52,"email":"rumbert15@toplist.cz","address":"2 Warbler Plaza"},
{"customer_id":43,"full_name":"Faulkner Semaine","age":49,"email":"fsemaine16@wordpress.org","address":"9406 Lindbergh Road"},
{"customer_id":44,"full_name":"Woody Golda","age":53,"email":"wgolda17@vimeo.com","address":"4 Petterle Point"},
{"customer_id":45,"full_name":"Tani Hulk","age":45,"email":"thulk18@quantcast.com","address":"12211 Oakridge Court"},
{"customer_id":46,"full_name":"Bee Eldridge","age":58,"email":"beldridge19@google.com.br","address":"1 Anzinger Plaza"},
{"customer_id":47,"full_name":"Aldric Swansbury","age":88,"email":"aswansbury1a@soup.io","address":"85844 Schmedeman Parkway"},
{"customer_id":48,"full_name":"Luelle Shafier","age":78,"email":"lshafier1b@hc360.com","address":"47 Hoepker Street"},
{"customer_id":49,"full_name":"Helena Ogle","age":50,"email":"hogle1c@digg.com","address":"5 Lotheville Court"},
{"customer_id":50,"full_name":"Stacey Spearing","age":68,"email":"sspearing1d@home.pl","address":"49014 Dovetail Alley"},
{"customer_id":51,"full_name":"Emmy Goodere","age":22,"email":"egoodere1e@tripadvisor.com","address":"81 Green Ridge Hill"},
{"customer_id":52,"full_name":"Gabbie Joynes","age":70,"email":"gjoynes1f@technorati.com","address":"90 Warner Street"},
{"customer_id":53,"full_name":"Carine Margeram","age":83,"email":"cmargeram1g@360.cn","address":"490 Dunning Center"},
{"customer_id":54,"full_name":"Dasi Pickering","age":69,"email":"dpickering1h@ucoz.com","address":"98 Rigney Way"},
{"customer_id":72,"full_name":"Cosette Kupper","age":48,"email":"ckupper1z@admin.ch","address":"363 Nova Parkway"},
{"customer_id":73,"full_name":"Aeriel Haslam","age":27,"email":"ahaslam20@diigo.com","address":"00836 Blue Bill Park Trail"},
{"customer_id":74,"full_name":"Hendrika Petett","age":73,"email":"hpetett21@clickbank.net","address":"058 Reindahl Court"},
{"customer_id":75,"full_name":"Chris Flarity","age":35,"email":"cflarity22@huffingtonpost.com","address":"3411 Corscot Point"},
{"customer_id":76,"full_name":"Leanora Treacy","age":57,"email":"ltreacy23@intel.com","address":"3207 Maple Wood Lane"},
{"customer_id":77,"full_name":"Goddard Walch","age":33,"email":"gwalch24@nifty.com","address":"0102 Chive Trail"},
{"customer_id":78,"full_name":"Brandais Dealy","age":29,"email":"bdealy25@nyu.edu","address":"3 Michigan Road"},
{"customer_id":79,"full_name":"Erinn Musker","age":46,"email":"emusker26@chron.com","address":"51994 Redwing Trail"},
{"customer_id":80,"full_name":"Diannne Fearnyhough","age":68,"email":"dfearnyhough27@51.la","address":"0 Homewood Court"},
{"customer_id":81,"full_name":"Cher Patriskson","age":79,"email":"cpatriskson28@friendfeed.com","address":"9897 Kings Center"},
{"customer_id":82,"full_name":"Reuben Mattiuzzi","age":43,"email":"rmattiuzzi29@theglobeandmail.com","address":"749 Independence Drive"},
{"customer_id":83,"full_name":"Lotta Tsar","age":56,"email":"ltsar2a@sphinn.com","address":"545 Messerschmidt Lane"},
{"customer_id":84,"full_name":"Nikki Tooke","age":56,"email":"ntooke2b@mit.edu","address":"0 Starling Trail"},
{"customer_id":85,"full_name":"Ezmeralda Elizabeth","age":66,"email":"eelizabeth2c@vistaprint.com","address":"12 Grover Parkway"},
{"customer_id":86,"full_name":"Naoma McLafferty","age":83,"email":"nmclafferty2d@slashdot.org","address":"79 Hintze Hill"},
{"customer_id":87,"full_name":"Aryn Trill","age":63,"email":"atrill2e@usda.gov","address":"00 Thierer Parkway"},
{"customer_id":88,"full_name":"Fredia Coldicott","age":88,"email":"fcoldicott2f@weebly.com","address":"85 Mccormick Parkway"},
{"customer_id":89,"full_name":"Roi Foxworthy","age":63,"email":"rfoxworthy2g@sun.com","address":"97 Ronald Regan Circle"},
{"customer_id":90,"full_name":"Vassili Eassom","age":61,"email":"veassom2h@latimes.com","address":"0 Eastlawn Place"},
{"customer_id":91,"full_name":"Jeramie Blais","age":36,"email":"jblais2i@devhub.com","address":"98 Everett Crossing"},
{"customer_id":92,"full_name":"Berni Large","age":22,"email":"blarge2j@infoseek.co.jp","address":"8024 Armistice Parkway"},
{"customer_id":93,"full_name":"Danna McCook","age":78,"email":"dmccook2k@wiley.com","address":"2 Merry Circle"},
{"customer_id":94,"full_name":"Neila Shackleton","age":68,"email":"nshackleton2l@paypal.com","address":"454 Hoffman Place"},
{"customer_id":95,"full_name":"Arri Harvey","age":54,"email":"aharvey2m@cyberchimps.com","address":"2820 Straubel Parkway"},
{"customer_id":96,"full_name":"Binni Colpus","age":79,"email":"bcolpus2n@tripod.com","address":"84656 Anniversary Trail"},
{"customer_id":97,"full_name":"Swen Dewan","age":35,"email":"sdewan2o@reference.com","address":"55 Sycamore Circle"},
{"customer_id":98,"full_name":"Flin Woodbridge","age":32,"email":"fwoodbridge2p@uol.com.br","address":"73 5th Street"},
{"customer_id":99,"full_name":"Micheal Fraschini","age":44,"email":"mfraschini2q@cisco.com","address":"44 Village Green Circle"},
{"customer_id":100,"full_name":"Daloris Gater","age":35,"email":"dgater2r@xinhuanet.com","address":"4042 Kings Parkway"}]